dropwise/__init__.py
dropwise/predictor.py
dropwise/tasks/__init__.py
dropwise/tasks/question_answering.py
dropwise/tasks/regression.py
dropwise/tasks/sequence_classification.py
dropwise/tasks/token_classification.py
dropwise-0.2.0.dist-info/licenses/LICENCE
dropwise-0.2.0.dist-info/METADATA
dropwise-0.2.0.dist-info/WHEEL
dropwise-0.2.0.dist-info/top_level.txt
dropwise-0.2.0.dist-info/RECORD
