Metadata-Version: 2.4
Name: dropwise
Version: 0.2.0
Summary: Monte Carlo Dropout-based uncertainty estimation for Transformers
Home-page: https://github.com/aryanator/dropwise
Author: Aryan Patil
Author-email: aryanator01@gmail.com
Classifier: Programming Language :: Python :: 3
Classifier: License :: OSI Approved :: MIT License
Classifier: Operating System :: OS Independent
Requires-Python: >=3.7
License-File: LICENCE
Requires-Dist: torch
Requires-Dist: transformers
Dynamic: author
Dynamic: author-email
Dynamic: classifier
Dynamic: description
Dynamic: description-content-type
Dynamic: home-page
Dynamic: license-file
Dynamic: requires-dist
Dynamic: requires-python
Dynamic: summary
